txtp/__init__.py
txtp/__main__.py
txtp/client.py
txtp/core.py
txtp/main.py
txtp/protocol.py
txtp/server.py
txtp-0.2.0.dist-info/licenses/LICENSE
txtp-0.2.0.dist-info/WHEEL
txtp-0.2.0.dist-info/METADATA
txtp-0.2.0.dist-info/RECORD
