Metadata-Version: 2.4
Name: txtp
Version: 0.2.0
Summary: A simple Text Transfer Protocol (TXTP) over TCP sockets.
Author-email: Rehan Sajid Hoque <idndteog19@gmail.com>
Requires-Python: >=3.8
License-File: LICENSE
Project-URL: Homepage, https://github.com/rsh46
Project-URL: Source, https://github.com/rsh46
